apistar_sentry.py
apistar_sentry-0.3.2.dist-info/DESCRIPTION.rst
apistar_sentry-0.3.2.dist-info/METADATA
apistar_sentry-0.3.2.dist-info/RECORD
apistar_sentry-0.3.2.dist-info/WHEEL
apistar_sentry-0.3.2.dist-info/metadata.json
apistar_sentry-0.3.2.dist-info/top_level.txt
