Metadata-Version: 2.0
Name: apistar-sentry
Version: 0.3.2
Summary: A Sentry component for API Star.
Home-page: UNKNOWN
License: UNKNOWN
Platform: UNKNOWN
Requires-Python: >=3.5
Requires-Dist: apistar (>=0.4)
Requires-Dist: raven
